recommend/__init__.py
recommend/filteringengine.py
recommend/history.py
recommend/location.py
recommend/recommendationengine.py
recommend/storageengine.py
recommend/user.py
recommend/usermanager.py
recommends-0.1.7.dist-info/LICENSE.txt
recommends-0.1.7.dist-info/METADATA
recommends-0.1.7.dist-info/WHEEL
recommends-0.1.7.dist-info/top_level.txt
recommends-0.1.7.dist-info/RECORD
