Metadata-Version: 2.1
Name: recommends
Version: 0.1.7
Summary: A library to enable one program a personalised recommendation system.
Home-page: https://github.com/bagumamuhsinkarim/recommend
Author: BAGUMA MUSHIN KARIM
Author-email: muhsinkarimbaguma@gmail.com
Classifier: Programming Language :: Python :: 3
Classifier: License :: OSI Approved :: MIT License
Classifier: Operating System :: OS Independent
License-File: LICENSE.txt
